tem_circlefind
