Metadata-Version: 1.0
Name: tem-circlefind
Version: 0.0.5
Summary: GUI utility for finding circles in images (especiall transmission electronmicrography)
Home-page: http://github.com/awacha/tem_circlefind
Author: Andras Wacha
Author-email: awacha@gmail.com
License: BSD 3-clause
Keywords: TEM,electron microscopy,circles,histogram
Platform: UNKNOWN
